pyms/Base.py
pyms/BillerBiemann.py
pyms/Display.py
pyms/Experiment.py
pyms/IntensityMatrix.py
pyms/IonChromatogram.py
pyms/Mixins.py
pyms/Simulator.py
pyms/Spectrum.py
pyms/TopHat.py
pyms/__init__.py
pyms/compat.py
pyms/eic.py
pyms/json.py
pyms/py.typed
pyms/DPA/Alignment.py
pyms/DPA/IO.py
pyms/DPA/PairwiseAlignment.py
pyms/DPA/__init__.py
pyms/DPA/clustering.py
pyms/GCMS/Class.py
pyms/GCMS/Function.py
pyms/GCMS/__init__.py
pyms/GCMS/IO/ANDI.py
pyms/GCMS/IO/JCAMP.py
pyms/GCMS/IO/MZML.py
pyms/GCMS/IO/__init__.py
pyms/Gapfill/Class.py
pyms/Gapfill/Function.py
pyms/Gapfill/__init__.py
pyms/Noise/Analysis.py
pyms/Noise/SavitzkyGolay.py
pyms/Noise/Window.py
pyms/Noise/__init__.py
pyms/Peak/Class.py
pyms/Peak/Function.py
pyms/Peak/__init__.py
pyms/Peak/List/Function.py
pyms/Peak/List/IO.py
pyms/Peak/List/__init__.py
pyms/Utils/IO.py
pyms/Utils/Math.py
pyms/Utils/Time.py
pyms/Utils/Utils.py
pyms/Utils/__init__.py
pyms/Utils/jcamp.py
pymassspec-2.7.0.post1.dist-info/AUTHORS
pymassspec-2.7.0.post1.dist-info/LICENSE
pymassspec-2.7.0.post1.dist-info/METADATA
pymassspec-2.7.0.post1.dist-info/WHEEL
pymassspec-2.7.0.post1.dist-info/top_level.txt
pymassspec-2.7.0.post1.dist-info/RECORD
