Metadata-Version: 2.1
Name: pymassspec
Version: 2.7.0.post1
Summary: Python Toolkit for Mass Spectrometry
Home-page: https://github.com/PyMassSpec/PyMassSpec
Author: Dominic Davis-Foster
Author-email: Dominic Davis-Foster <dominic@davis-foster.co.uk>
License: GNU GENERAL PUBLIC LICENSE
Project-URL: Homepage, https://github.com/PyMassSpec/PyMassSpec
Project-URL: Issue Tracker, https://github.com/PyMassSpec/PyMassSpec/issues
Project-URL: Source Code, https://github.com/PyMassSpec/PyMassSpec
Project-URL: Documentation, https://pymassspec.readthedocs.io/en/latest
Keywords: chemistry,chromatography,mass-spectrometry
Platform: Windows
Platform: macOS
Platform: Linux
Classifier: Development Status :: 5 - Production/Stable
Classifier: Intended Audience :: Developers
Classifier: Intended Audience :: Education
Classifier: Intended Audience :: End Users/Desktop
Classifier: Intended Audience :: Science/Research
Classifier: License :: OSI Approved :: GNU General Public License v2 (GPLv2)
Classifier: Operating System :: OS Independent
Classifier: Programming Language :: Python
Classifier: Programming Language :: Python :: 3 :: Only
Classifier: Programming Language :: Python :: 3.7
Classifier: Programming Language :: Python :: 3.8
Classifier: Programming Language :: Python :: 3.9
Classifier: Programming Language :: Python :: 3.10
Classifier: Programming Language :: Python :: 3.11
Classifier: Programming Language :: Python :: 3.12
Classifier: Programming Language :: Python :: 3.13
Classifier: Programming Language :: Python :: Implementation :: CPython
Classifier: Topic :: Education
Classifier: Topic :: Scientific/Engineering :: Bio-Informatics
Classifier: Topic :: Scientific/Engineering :: Chemistry
Classifier: Topic :: Software Development :: Libraries :: Python Modules
Classifier: Typing :: Typed
Requires-Python: >=3.7
License-File: LICENSE
License-File: AUTHORS
Requires-Dist: biopython>=1.74
Requires-Dist: deprecation>=2.1.0
Requires-Dist: domdf-python-tools>=1.7.0
Requires-Dist: enum-tools>=0.6.1
Requires-Dist: netcdf4>=1.5.0
Requires-Dist: openpyxl>=2.6.2
Requires-Dist: pandas>=1.0.0
Requires-Dist: scipy>=1.2.1
Requires-Dist: sdjson>=0.3.0
Requires-Dist: typing-extensions>=3.7.4.3
Requires-Dist: matplotlib>=3.2.2; platform_machine != "aarch64" or python_version > "3.6"
Requires-Dist: matplotlib==3.2.2; platform_machine == "aarch64" and python_version == "3.6"
Requires-Dist: numpy>=1.19.2; platform_system != "Windows"
Requires-Dist: numpy!=1.19.4,>=1.19.3; platform_system == "Windows"
Requires-Dist: pymzml<2.6.0,>=2.2.1; python_version < "3.8"
Requires-Dist: cftime<=1.3.0; python_version == "3.6" and platform_system == "Windows"
Requires-Dist: pymzml>=2.2.1; python_version >= "3.8"
